trame/LICENSE
trame/__init__.py
trame/decorators.py
trame/app/__init__.py
trame/app/asynchronous.py
trame/app/core.py
trame/app/demo.py
trame/app/dev.py
trame/app/file_upload.py
trame/app/jupyter.py
trame/app/jupyter_css.py
trame/app/klass.py
trame/app/mimetypes.py
trame/app/pv_demo.py
trame/app/singleton.py
trame/app/testing.py
trame/assets/__init__.py
trame/assets/local.py
trame/assets/mimetypes.py
trame/assets/remote.py
trame/env/__init__.py
trame/env/paraview.py
trame/env/utils.py
trame/env/venv.py
trame/modules/__init__.py
trame/tools/__init__.py
trame/tools/app.py
trame/tools/serve.py
trame/tools/vtk.py
trame/tools/www.py
trame/tools/widgets/__init__.py
trame/tools/widgets/__main__.py
trame/tools/widgets/generator.py
trame/tools/widgets/utils.py
trame/ui/__init__.py
trame/utils/__init__.py
trame/utils/asynchronous.py
trame/utils/exec.py
trame/utils/version.py
trame/widgets/__init__.py
trame/widgets/helper.py
trame-3.11.0.dist-info/licenses/LICENSE
trame-3.11.0.dist-info/METADATA
trame-3.11.0.dist-info/WHEEL
trame-3.11.0.dist-info/top_level.txt
trame-3.11.0.dist-info/RECORD
