Metadata-Version: 2.4
Name: trame
Version: 3.11.0
Summary: Trame, a framework to build applications in plain Python
Author: Kitware Inc.
License: Apache License 2.0
Keywords: Python,Interactive,Web,Application,Framework
Classifier: Development Status :: 5 - Production/Stable
Classifier: Environment :: Web Environment
Classifier: License :: OSI Approved :: Apache Software License
Classifier: Natural Language :: English
Classifier: Operating System :: OS Independent
Classifier: Programming Language :: Python :: 3 :: Only
Classifier: Topic :: Software Development :: Libraries :: Application Frameworks
Classifier: Topic :: Software Development :: Libraries :: Python Modules
Requires-Python: >=3.9
License-File: LICENSE
Requires-Dist: trame-server<4,>=3.4
Requires-Dist: trame-client<4,>=3.8
Requires-Dist: trame-common<2,>=1
Requires-Dist: wslink>=2.3.3
Requires-Dist: pyyaml
Provides-Extra: app
Requires-Dist: pywebview; extra == "app"
Provides-Extra: jupyter
Requires-Dist: jupyterlab; extra == "jupyter"
Provides-Extra: dev
Requires-Dist: pre-commit; extra == "dev"
Requires-Dist: ruff; extra == "dev"
Requires-Dist: pytest; extra == "dev"
Dynamic: license-file
